[
	{
		"pid": 1,
		"p_name": "Structural Engineer",
		"p_salary": 6690.01
	},
	{
		"pid": 2,
		"p_name": "Product Engineer",
		"p_salary": 5637.78
	},
	{
		"pid": 3,
		"p_name": "Quality Engineer",
		"p_salary": 7939.72
	},
	{
		"pid": 4,
		"p_name": "Compensation Analyst",
		"p_salary": 5045.6
	},
	{
		"pid": 5,
		"p_name": "Design Engineer",
		"p_salary": 6573.99
	},
	{
		"pid": 6,
		"p_name": "Help Desk Operator",
		"p_salary": 7911.08
	},
	{
		"pid": 7,
		"p_name": "Statistician II",
		"p_salary": 7292.74
	},
	{
		"pid": 8,
		"p_name": "Registered Nurse",
		"p_salary": 4133.88
	},
	{
		"pid": 9,
		"p_name": "Staff Accountant I",
		"p_salary": 5827.93
	},
	{
		"pid": 10,
		"p_name": "Nurse",
		"p_salary": 7835.44
	},
	{
		"pid": 11,
		"p_name": "Statistician IV",
		"p_salary": 4521.47
	},
	{
		"pid": 12,
		"p_name": "Programmer IV",
		"p_salary": 6913.31
	},
	{
		"pid": 13,
		"p_name": "Technical Writer",
		"p_salary": 7613.53
	},
	{
		"pid": 14,
		"p_name": "Associate Professor",
		"p_salary": 4283.28
	},
	{
		"pid": 15,
		"p_name": "Design Engineer",
		"p_salary": 6239.85
	},
	{
		"pid": 16,
		"p_name": "Structural Analysis Engineer",
		"p_salary": 5280.98
	},
	{
		"pid": 17,
		"p_name": "Account Representative III",
		"p_salary": 7213.04
	},
	{
		"pid": 18,
		"p_name": "Director of Sales",
		"p_salary": 6986.45
	},
	{
		"pid": 19,
		"p_name": "Operator",
		"p_salary": 5367.5
	},
	{
		"pid": 20,
		"p_name": "Electrical Engineer",
		"p_salary": 4526.81
	}
]